[
  {
    "username": "titus",
    "email": "titus@gmail.com",
    "password": "titus123",
    "profile": "https://placehold.co/120x120?text=Titus",
    "background": "https://placehold.co/600x300?text=Background",
    "availability": "10:00 AM - 12:00 PM",
    "location": "13째03'15.8"N 80째06'42.1"E"
  },
  {
    "username": "devatitus",
    "email": "deva@gmail.com",
    "password": "deva123",
    "profile": "https://placehold.co/120x120?text=Deva",
    "background": "https://placehold.co/600x300?text=Background",
    "availability": "9:00 AM - 5:00 PM",
    "location": "13째03'15.8"N 80째06'42.1"E"
  }
]
